geoapify4us/__init__.py
geoapify4us/geoapify4us.py
geoapify4us-0.0.2.dist-info/METADATA
geoapify4us-0.0.2.dist-info/WHEEL
geoapify4us-0.0.2.dist-info/top_level.txt
geoapify4us-0.0.2.dist-info/RECORD
