Metadata-Version: 2.1
Name: geoapify4us
Version: 0.0.2
Summary: Codes to help using GeoAPIfy APIs
Home-page: https://github.com/anespart1/Geoapify4us
Author: Shin Daeyong
Author-email: anespartgis@gmail.com
License: MIT
Platform: UNKNOWN
Classifier: Programming Language :: Python :: 3
Classifier: Programming Language :: Python :: 3.2
Classifier: Programming Language :: Python :: 3.3
Classifier: Programming Language :: Python :: 3.4
Classifier: Programming Language :: Python :: 3.5
Classifier: Programming Language :: Python :: 3.6
Classifier: Programming Language :: Python :: 3.7
Requires-Python: >=3
Requires-Dist: re
Requires-Dist: urllib
Requires-Dist: json
